MANIFEST.in
README.rst
requirements.txt
setup.py
smartfile/__init__.py
smartfile/errors.py
smartfile/sync.py
smartfile.egg-info/PKG-INFO
smartfile.egg-info/SOURCES.txt
smartfile.egg-info/dependency_links.txt
smartfile.egg-info/requires.txt
smartfile.egg-info/top_level.txt
test/test_smartfile.py