Metadata-Version: 1.1
Name: smartfile
Version: 2.19
Summary: A Python client for the SmartFile API.
Home-page: http://github.com/smartfile/client-python/
Author: Ben Timby
Author-email: tech@smartfile.com
License: MIT
Platform: UNKNOWN
Classifier: Development Status :: 4 - Beta
Classifier: Intended Audience :: Developers
Classifier: Operating System :: OS Independent
Classifier: Programming Language :: Python
Classifier: Topic :: Software Development :: Libraries :: Python Modules
